{
  "_id": "5792aa75b257d584089ef250",
  "isPublish": true,
  "formNo": "RF-750-010-327",
  "formRev": "09",
  "customer": "CHECK POINT",
  "itemRecord": [
    {
      "Description": "HTO",
      "id": 1
    },
    {
      "Description": "FID",
      "id": 2
    },
    {
      "select": {
        "options": [
          "UTM",
          "POWER",
          "VSX",
          "CONNECTRA",
          "IPS",
          "DLP",
          "RUSSIA",
          "U10 (CP 270)",
          "MU20 (CP 570)",
          "U20 (CP 1070)",
          "U30 (CP 2070)",
          "U40 (CP 3070)",
          "P-10 (CP 5070)",
          "P-20 (CP 9070)",
          "P-30 (CP 11070)",
          "P-110 (CP 2200)",
          "T-120 (CP 4200)",
          "T-140 (CP 4400)",
          "T-160 (CP 4600)",
          "T-180 (CP 4800)",
          "P-210 (CP 12200)",
          "P-220 (CP 12400)",
          "P-230 (CP 12600)",
          "VSX_P210 (CP 12200 VSX)",
          "VSX_P220 (CP 12400 VSX)",
          "VSX_P230(CP 12600 VSX)"
        ],
        "name": ""
      },
      "Description": "Product Model",
      "id": 3
    },
    {
      "select": {
        "options": [
          "PB-10",
          "PB-20",
          "PL-10",
          "PL-20",
          "PL-30"
        ],
        "name": ""
      },
      "Description": "Panther",
      "id": 4
    },
    {
      "Description": "SW VER",
      "id": 5
    },
    {
      "Description": "SO#",
      "id": 6
    },
    {
      "Description": "MAC#",
      "id": 7
    },
    {
      "Description": "Remark",
      "id": 8
    }
  ],
  "steps": [
    {
      "list": [
        {
          "options": [
            {
              "options": [
                "Checked",
                "Damaged/Replaced"
              ],
              "name": "Check List",
              "type": "checkbox"
            }
          ],
          "Description": "Outer Box",
          "sub_step": 1
        },
        {
          "options": [
            {
              "options": [
                "Checked"
              ],
              "name": "Check List",
              "type": "checkbox"
            }
          ],
          "Description": "Inner Carton and Form",
          "sub_step": 2
        },
        {
          "options": [
            {
              "options": [
                "Checked",
                "Damaged/ Put Aside-RMA"
              ],
              "name": "Check List",
              "type": "checkbox"
            }
          ],
          "Description": "Appliance Surface Cosmetic & LCD Inspection",
          "sub_step": 3
        },
        {
          "options": [
            {
              "options": [
                "Checked"
              ],
              "name": "Check List",
              "type": "checkbox"
            }
          ],
          "Description": "All Screws Assembly Well",
          "sub_step": 4
        },
        {
          "options": [
            {
              "options": [
                "Checked"
              ],
              "name": "Check List",
              "type": "checkbox"
            }
          ],
          "Description": "Release Note",
          "sub_step": 5
        },
        {
          "options": [
            {
              "options": [
                "Checked"
              ],
              "name": "Check List",
              "type": "checkbox"
            }
          ],
          "Description": "Assembly Kit",
          "sub_step": 6
        },
        {
          "options": [
            {
              "options": [
                "Checked"
              ],
              "name": "Check List",
              "type": "checkbox"
            }
          ],
          "Description": "Warranty Label",
          "sub_step": 7
        }
      ],
      "Description": "Initial Visual Inspection",
      "type": "IQC",
      "step": 1
    },
    {
      "list": [
        {
          "options": [
            {
              "options": [
                "Passed",
                "Failed",
                "Upload Test Log to Server",
                "Put Aside and Issue RMA"
              ],
              "name": "Check List",
              "type": "checkbox"
            }
          ],
          "Description": "CVER Test",
          "sub_step": 1
        },
        {
          "options": [
            {
              "options": [
                "Passed",
                "Failed",
                "Upload Test Log to Server",
                "Put Aside and Issue RMA"
              ],
              "name": "Check List",
              "type": "checkbox"
            }
          ],
          "Description": "SW Version & Log in Screen Check",
          "sub_step": 2
        },
        {
          "options": [
            {
              "options": [
                "Passed",
                "Failed",
                "Upload Test Log to Server",
                "Put Aside and Issue RMA"
              ],
              "name": "Check List",
              "type": "checkbox"
            }
          ],
          "Description": "LCD Check",
          "sub_step": 3
        },
        {
          "options": [
            {
              "options": [
                "Passed",
                "Failed",
                "Upload Test Log to Server",
                "Put Aside and Issue RMA"
              ],
              "name": "Check List",
              "type": "checkbox"
            }
          ],
          "Description": "FAN Check",
          "sub_step": 4
        },
        {
          "options": [
            {
              "options": [
                "Passed",
                "Failed",
                "Upload Test Log to Server",
                "Put Aside and Issue RMA"
              ],
              "name": "Check List",
              "type": "checkbox"
            }
          ],
          "Description": "LOM Test",
          "sub_step": 5
        },
        {
          "options": [
            {
              "options": [
                "Passed",
                "Failed",
                "Upload Test Log to Server",
                "Put Aside and Issue RMA"
              ],
              "name": "Check List",
              "type": "checkbox"
            }
          ],
          "Description": "PSU Check",
          "sub_step": 6
        }
      ],
      "Description": "",
      "type": "IQC",
      "step": 2
    },
    {
      "list": [
        {
          "options": [
            {
              "options": [
                "Checked"
              ],
              "name": "Check List",
              "type": "checkbox"
            }
          ],
          "Description": "Appliance SN matched with Box SN",
          "sub_step": 1
        },
        {
          "options": [
            {
              "options": [
                "Checked"
              ],
              "name": "Check List",
              "type": "checkbox"
            }
          ],
          "Description": "Plastic Bag in Good Condition",
          "sub_step": 2
        },
        {
          "options": [
            {
              "options": [
                "Checked"
              ],
              "name": "Check List",
              "type": "checkbox"
            }
          ],
          "Description": "All Screws Assembly Welll",
          "sub_step": 3
        },
        {
          "options": [
            {
              "options": [
                "Checked"
              ],
              "name": "Check List",
              "type": "checkbox"
            }
          ],
          "Description": "Warranty Well",
          "sub_step": 4
        },
        {
          "options": [
            {
              "options": [
                "Checked"
              ],
              "name": "Check List",
              "type": "checkbox"
            }
          ],
          "Description": "Sealed the Box",
          "sub_step": 5
        }
      ],
      "Description": "Packaging Check",
      "type": "IQC",
      "step": 3
    },
    {
      "list": [
        {
          "options": [
            {
              "options": [
                "309848"
              ],
              "name": "PN",
              "type": "checkbox"
            },
            {
              "options": [
                "Installed",
                "Ship Alone"
              ],
              "name": "Check List",
              "type": "checkbox"
            }
          ],
          "Description": "CPAC-4-1C",
          "sub_step": 1
        },
        {
          "options": [
            {
              "options": [
                "309818",
                "317275"
              ],
              "name": "PN",
              "type": "checkbox"
            },
            {
              "options": [
                "Installed",
                "Ship Alone"
              ],
              "name": "Check List",
              "type": "checkbox"
            }
          ],
          "Description": "CPAC-8-1C/B",
          "sub_step": 2
        },
        {
          "options": [
            {
              "options": [
                "309816",
                "317272"
              ],
              "name": "PN",
              "type": "checkbox"
            },
            {
              "options": [
                "Installed",
                "Ship Alone"
              ],
              "name": "Check List",
              "type": "checkbox"
            }
          ],
          "Description": "CPAC-4-1F/B",
          "sub_step": 3
        },
        {
          "options": [
            {
              "options": [
                "309817",
                "317271"
              ],
              "name": "PN",
              "type": "checkbox"
            },
            {
              "options": [
                "Installed",
                "Ship Alone"
              ],
              "name": "Check List",
              "type": "checkbox"
            }
          ],
          "Description": "CPAC-4-10F/B",
          "sub_step": 4
        },
        {
          "options": [
            {
              "options": [
                "309911"
              ],
              "name": "PN",
              "type": "checkbox"
            },
            {
              "options": [
                "Installed",
                "Ship Alone"
              ],
              "name": "Check List",
              "type": "checkbox"
            }
          ],
          "Description": "CPAC-2-1F",
          "sub_step": 5
        },
        {
          "options": [
            {
              "options": [
                "309847",
                "317270"
              ],
              "name": "PN",
              "type": "checkbox"
            },
            {
              "options": [
                "Installed",
                "Ship Alone"
              ],
              "name": "Check List",
              "type": "checkbox"
            }
          ],
          "Description": "CPAC-2-10F/B",
          "sub_step": 6
        },
        {
          "options": [
            {
              "options": [
                "311577",
                "317350"
              ],
              "name": "PN",
              "type": "checkbox"
            },
            {
              "options": [
                "Installed",
                "Ship Alone"
              ],
              "name": "Check List",
              "type": "checkbox"
            }
          ],
          "Description": "CPAC-4-1C-BP/B",
          "sub_step": 7
        },
        {
          "options": [
            {
              "options": [
                "311579"
              ],
              "name": "PN",
              "type": "checkbox"
            },
            {
              "options": [
                "Installed",
                "Ship Alone"
              ],
              "name": "Check List",
              "type": "checkbox"
            }
          ],
          "Description": "CPAC-4-1FSR-BP",
          "sub_step": 8
        },
        {
          "options": [
            {
              "options": [
                "311582"
              ],
              "name": "PN",
              "type": "checkbox"
            },
            {
              "options": [
                "Installed",
                "Ship Alone"
              ],
              "name": "Check List",
              "type": "checkbox"
            }
          ],
          "Description": "CPAC-4-1FLR-BP",
          "sub_step": 9
        },
        {
          "options": [
            {
              "options": [
                "311590"
              ],
              "name": "PN",
              "type": "checkbox"
            },
            {
              "options": [
                "Installed",
                "Ship Alone"
              ],
              "name": "Check List",
              "type": "checkbox"
            }
          ],
          "Description": "CPAC-2-10FLR-BP",
          "sub_step": 10
        },
        {
          "options": [
            {
              "options": [
                "311587",
                "317348"
              ],
              "name": "PN",
              "type": "checkbox"
            },
            {
              "options": [
                "Installed",
                "Ship Alone"
              ],
              "name": "Check List",
              "type": "checkbox"
            }
          ],
          "Description": "CPAC-2-10FSR-BP/B",
          "sub_step": 11
        },
        {
          "options": [
            {
              "options": [
                "317269"
              ],
              "name": "PN",
              "type": "checkbox"
            },
            {
              "options": [
                "Installed",
                "Ship Alone"
              ],
              "name": "Check List",
              "type": "checkbox"
            }
          ],
          "Description": "CPAC-2-40P-B",
          "sub_step": 12
        }
      ],
      "Description": "Expansion Cards",
      "type": "OQC",
      "step": 4
    },
    {
      "list": [
        {
          "options": [
            {
              "options": [
                "309855",
                "317354"
              ],
              "name": "PN",
              "type": "checkbox"
            },
            {
              "options": [
                "Ship Alone"
              ],
              "name": "Check List",
              "type": "checkbox"
            }
          ],
          "Description": "CPAC-TR-1LX/B",
          "sub_step": 1
        },
        {
          "options": [
            {
              "options": [
                "309821",
                "317355"
              ],
              "name": "PN",
              "type": "checkbox"
            },
            {
              "options": [
                "Ship Alone"
              ],
              "name": "Check List",
              "type": "checkbox"
            }
          ],
          "Description": "CPAC-TR-1SX/B",
          "sub_step": 2
        },
        {
          "options": [
            {
              "options": [
                "309822",
                "317353"
              ],
              "name": "PN",
              "type": "checkbox"
            },
            {
              "options": [
                "Ship Alone"
              ],
              "name": "Check List",
              "type": "checkbox"
            }
          ],
          "Description": "CPAC-TR-10SR/B",
          "sub_step": 3
        },
        {
          "options": [
            {
              "options": [
                "309856",
                "317352"
              ],
              "name": "PN",
              "type": "checkbox"
            },
            {
              "options": [
                "Ship Alone"
              ],
              "name": "Check List",
              "type": "checkbox"
            }
          ],
          "Description": "CPAC-TR-10LR/B",
          "sub_step": 4
        },
        {
          "options": [
            {
              "options": [
                "309869",
                "317356"
              ],
              "name": "PN",
              "type": "checkbox"
            },
            {
              "options": [
                "Ship Alone"
              ],
              "name": "Check List",
              "type": "checkbox"
            }
          ],
          "Description": "CPAC-TR-1T/B",
          "sub_step": 5
        },
        {
          "options": [
            {
              "options": [
                "316655"
              ],
              "name": "PN",
              "type": "checkbox"
            },
            {
              "options": [
                "Ship Alone"
              ],
              "name": "Check List",
              "type": "checkbox"
            }
          ],
          "Description": "CPAC-TR-40LR-QSFP-10Km",
          "sub_step": 6
        },
        {
          "options": [
            {
              "options": [
                "316654"
              ],
              "name": "PN",
              "type": "checkbox"
            },
            {
              "options": [
                "Ship Alone"
              ],
              "name": "Check List",
              "type": "checkbox"
            }
          ],
          "Description": "CPAC-TR-40SR-QSFP-300m",
          "sub_step": 7
        }
      ],
      "Description": "Optical Transceivers",
      "type": "OQC",
      "step": 5
    },
    {
      "list": [
        {
          "options": [
            {
              "options": [
                "Passed",
                "Upload Test Log to server",
                "Failed",
                "Put Aside and Issue RMA"
              ],
              "name": "Check List",
              "type": "checkbox"
            }
          ],
          "Description": "CVER Test",
          "sub_step": 1
        }
      ],
      "Description": "EVER Test",
      "type": "OQC",
      "step": 6
    },
    {
      "list": [
        {
          "options": [
            {
              "options": [
                "Checked"
              ],
              "name": "Check List",
              "type": "checkbox"
            }
          ],
          "Description": "Software Testing Procedure (Refer to Model SOP)",
          "sub_step": 1
        }
      ],
      "Description": "Software Testing Procedure(Refer to Model SOP)",
      "type": "OQC",
      "step": 7
    },
    {
      "list": [
        {
          "options": [
            {
              "options": [
                "Installed",
                "Ship Alone"
              ],
              "name": "Check List",
              "type": "checkbox"
            }
          ],
          "Description": "CPAC-RAM4GB for 4600/4800/12200 (PN 309934)",
          "sub_step": 1
        },
        {
          "options": [
            {
              "options": [
                "Installed",
                "Ship Alone"
              ],
              "name": "Check List",
              "type": "checkbox"
            }
          ],
          "Description": "CPAC-RAM4GB-12400 FOR 12400 (PN 309935)",
          "sub_step": 2
        },
        {
          "options": [
            {
              "options": [
                "Installed",
                "Ship Alone"
              ],
              "name": "Check List",
              "type": "checkbox"
            }
          ],
          "Description": "CPAC-RAM6GB-12600 FOR 12600 (PN 310189)",
          "sub_step": 3
        },
        {
          "options": [
            {
              "options": [
                "Installed",
                "Ship Alone"
              ],
              "name": "Check List",
              "type": "checkbox"
            }
          ],
          "Description": "CPAC-RAM8GB-5000 (PN 317280)",
          "sub_step": 4
        }
      ],
      "Description": "Memory",
      "type": "OQC",
      "step": 8
    },
    {
      "list": [
        {
          "options": [
            {
              "options": [
                "Installed",
                "Ship Alone"
              ],
              "name": "Check List",
              "type": "checkbox"
            }
          ],
          "Description": "CPAC-LOM-B (PN 317357)",
          "sub_step": 1
        }
      ],
      "Description": "",
      "type": "OQC",
      "step": 9
    },
    {
      "list": [
        {
          "options": [
            {
              "options": [
                "Installed",
                "Ship Alone"
              ],
              "name": "Check List",
              "type": "checkbox"
            }
          ],
          "Description": "CPAP-PSU-4800B/12200B (PN 316658)",
          "sub_step": 1
        },
        {
          "options": [
            {
              "options": [
                "Installed",
                "Ship Alone"
              ],
              "name": "Check List",
              "type": "checkbox"
            }
          ],
          "Description": "CPAC-PSU-3200/2200 (PN 317286)",
          "sub_step": 2
        },
        {
          "options": [
            {
              "options": [
                "Installed",
                "Ship Alone"
              ],
              "name": "Check List",
              "type": "checkbox"
            }
          ],
          "Description": "CPAC-PSU-5600/5800/4800/12200 (PN 317280)",
          "sub_step": 3
        }
      ],
      "Description": "PSU",
      "type": "OQC",
      "step": 10
    },
    {
      "list": [
        {
          "options": [
            {
              "options": [
                "Installed",
                "RAID SYNC",
                "Ship Alone"
              ],
              "name": "Check List",
              "type": "checkbox"
            }
          ],
          "Description": "CPAC-HDD-500G-12200-T (PN 313286)",
          "sub_step": 1
        },
        {
          "options": [
            {
              "options": [
                "Installed",
                "RAID SYNC",
                "Ship Alone"
              ],
              "name": "Check List",
              "type": "checkbox"
            }
          ],
          "Description": "CPAC-HDD-500G-12400-T (PN 313285)",
          "sub_step": 2
        }
      ],
      "Description": "HDD ADD ON",
      "type": "OQC",
      "step": 11
    },
    {
      "list": [
        {
          "options": [
            {
              "options": [
                "Checked"
              ],
              "name": "Check List",
              "type": "checkbox"
            }
          ],
          "Description": "Check power cord type (if installed PSU, add one more)",
          "sub_step": 1
        },
        {
          "options": [
            {
              "options": [
                "Checked"
              ],
              "name": "Check List",
              "type": "checkbox"
            }
          ],
          "Description": "Appliance SN matched with BOX SN",
          "sub_step": 2
        },
        {
          "options": [
            {
              "options": [
                "Checked"
              ],
              "name": "Check List",
              "type": "checkbox"
            }
          ],
          "Description": "Plastic Bag in Good Condition",
          "sub_step": 3
        },
        {
          "options": [
            {
              "options": [
                "Checked"
              ],
              "name": "Check List",
              "type": "checkbox"
            }
          ],
          "Description": "All Screws Assembly Well",
          "sub_step": 4
        },
        {
          "options": [
            {
              "options": [
                "Checked"
              ],
              "name": "Check List",
              "type": "checkbox"
            }
          ],
          "Description": "Warranty Label",
          "sub_step": 5
        },
        {
          "options": [
            {
              "options": [
                "Checked"
              ],
              "name": "Check List",
              "type": "checkbox"
            }
          ],
          "Description": "Sealed the Box",
          "sub_step": 6
        }
      ],
      "Description": "Packaging Check",
      "type": "OQC",
      "step": 12
    }
  ],
  "__v": 0
}